doc/m.py
doc/p.py
prodpadlm_client/__init__.py
prodpadlm_client/client.py
prodpadlm_client/client_types/__init__.py
prodpadlm_client/client_types/_types.py
prodpadlm_client/client_types/messages.py
prodpadlm_client/client_types/stream_messages.py
prodpadlm_client/resources/__init__.py
prodpadlm_client/resources/api.py
prodpadlm_client-0.1.1.5.1.dist-info/LICENSE.txt
prodpadlm_client-0.1.1.5.1.dist-info/METADATA
prodpadlm_client-0.1.1.5.1.dist-info/WHEEL
prodpadlm_client-0.1.1.5.1.dist-info/top_level.txt
prodpadlm_client-0.1.1.5.1.dist-info/RECORD
