Metadata-Version: 2.1
Name: prodpadlm_client
Version: 0.1.1.5.1
Summary: Production LaunchPad for Language Models [Client] - ⚡ Ship Open Source LLMs to production faster and efficiently ⚡
Author-email: Ayo Kehinde Samuel <samkehindeayo@gmail.com>
License: Apache License
Project-URL: Documentation, https://readthedocs.org
Project-URL: Repository, https://github.com/Stosan/prodpadlm-client.git
Project-URL: Issues, https://github.com/Stosan/prodpadlm-client/issues
Project-URL: Changelog, https://github.com/Stosan/prodpadlm-client/CHANGELOG.md
Classifier: Programming Language :: Python :: 3
Classifier: License :: OSI Approved :: MIT License
Classifier: Operating System :: OS Independent
Requires-Python: >=3.9
License-File: LICENSE.txt
Requires-Dist: httpx
Requires-Dist: pydantic-settings
Requires-Dist: langchain
Requires-Dist: langchain-core
